<?xml version="1.0" encoding="ISO-8859-1"?>
<!-- XML generated by UTFXML Version 2.2 built 19-Aug-2010 -->
<UTFXML filename="bm_f_zsu.cmp" path="BMOD\EQUIPMENT\MODELS\TURRETS">
   <UTF_ROOT>
      <VMeshLibrary>
         <bm_f_zsu_1_.lod0-112.vms name="bm_f_zsu(1).lod0-112.vms" include="bm_f_zsu_cmp\lod0-112.vms.xml"/>
      </VMeshLibrary>
      <Exporter_Version name="Exporter Version" type="text">MAXLancer Tools 0.98</Exporter_Version>
      <Cmpnd>
         <Cons>
            <Fix type="Fix" count="1">
               <part>
                  <!-- parent      --> "Root",
                  <!-- child       --> "Barrel",
                  <!-- position    --> 0, 0, 0,
                  <!-- orientation -->   1.0000000000,   0.0000000000,   0.0000000000,
                                         0.0000000000,   1.0000000000,   0.0000000000,
                                         0.0000000000,   0.0000000000,   1.0000000000
               </part>
            </Fix>
         </Cons>
         <Part_Barrel>
            <Object_name name="Object name" type="text">Barrel</Object_name>
            <Index type="int">0</Index>
            <File_name name="File name" type="text">Barrel240615163511.3db</File_name>
         </Part_Barrel>
         <Root>
            <Object_name name="Object name" type="text">Root</Object_name>
            <Index type="int">0</Index>
            <File_name name="File name" type="text">bm_f_zsu(1)240615163511.3db</File_name>
         </Root>
      </Cmpnd>
      <bm_f_zsu_1_240615163511.3db name="bm_f_zsu(1)240615163511.3db">
         <VMeshPart>
            <VMeshRef type="VMeshRef">
               <!-- header size  --> 60,
               <!-- vmesh lib    --> bm_f_zsu(1).lod0-112.vms,
               <!-- start vert   --> 0,
               <!-- num verts    --> 218,
               <!-- start index  --> 0,
               <!-- num indices  --> 336,
               <!-- start mesh   --> 0,
               <!-- num meshes   --> 3,
               <!-- bounding box -->   1.9348969,    1.8899947,   1.8050983,
                                      -1.9348969,   -0.39144081, -1.8492208,
               <!-- center       --> -92.112045e-6,  0.95683122,  0.26558599,
               <!-- radius       --> 2.9085956
            </VMeshRef>
         </VMeshPart>
         <VMeshWire include="bm_f_zsu_cmp\bm_f_zsu(1).vwd.xml"/>
         <Hardpoints>
            <Revolute>
               <HpConnect>
                  <Orientation type="Matrix">
                       1.0000000000,   0.0000000000,   0.0000000000,
                       0.0000000000,   1.0000000000,   0.0000000000,
                       0.0000000000,   0.0000000000,   1.0000000000
                  </Orientation>
                  <Position type="Vector">0, -0.45421094, 0</Position>
                  <Axis type="Vector">0, 1, 0</Axis>
                  <Min type="float">-6.2831855</Min>
                  <Max type="float">6.2831855</Max>
               </HpConnect>
            </Revolute>
         </Hardpoints>
      </bm_f_zsu_1_240615163511.3db>
      <Barrel240615163511.3db>
         <VMeshPart>
            <VMeshRef type="VMeshRef">
               <!-- header size  --> 60,
               <!-- vmesh lib    --> bm_f_zsu(1).lod0-112.vms,
               <!-- start vert   --> 218,
               <!-- num verts    --> 1815,
               <!-- start index  --> 336,
               <!-- num indices  --> 1815,
               <!-- start mesh   --> 3,
               <!-- num meshes   --> 3,
               <!-- bounding box -->  0.85889286,   1.8574057,   0.43810025,
                                     -0.88330984,   0.47050905, -7.1367025,
               <!-- center       --> -0.0038023517, 1.0595715,  -2.9220281,
               <!-- radius       --> 4.2813706
            </VMeshRef>
         </VMeshPart>
         <VMeshWire include="bm_f_zsu_cmp\Barrel.vwd.xml"/>
         <Hardpoints>
            <Fixed>
               <HpFire01>
                  <Orientation type="Matrix">
                       1.0000000000,   0.0000000000,   0.0000000000,
                       0.0000000000,   1.0000000000,   0.0000000000,
                       0.0000000000,   0.0000000000,   1.0000000000
                  </Orientation>
                  <Position type="Vector">-0.50195318, 0.7174806, -7.1586437</Position>
               </HpFire01>
               <HpFire02>
                  <Orientation type="Matrix">
                       1.0000000000,   0.0000000000,   0.0000000000,
                       0.0000000000,   1.0000000000,  -0.0000000000,
                      -0.0000000000,   0.0000000000,   1.0000000000
                  </Orientation>
                  <Position type="Vector">0.50195318, 0.7174806, -7.1586437</Position>
               </HpFire02>
               <HpFire03>
                  <Orientation type="Matrix">
                       1.0000000000,   0.0000000000,   0.0000000000,
                       0.0000000000,   1.0000000000,   0.0000000000,
                       0.0000000000,   0.0000000000,   1.0000000000
                  </Orientation>
                  <Position type="Vector">-0.50195318, 1.3001639, -7.1586437</Position>
               </HpFire03>
               <HpFire04>
                  <Orientation type="Matrix">
                       1.0000000000,   0.0000000000,   0.0000000000,
                       0.0000000000,   1.0000000000,  -0.0000000000,
                      -0.0000000000,   0.0000000000,   1.0000000000
                  </Orientation>
                  <Position type="Vector">0.50195318, 1.3001639, -7.1586437</Position>
               </HpFire04>
            </Fixed>
         </Hardpoints>
      </Barrel240615163511.3db>
   </UTF_ROOT>
</UTFXML>
