<?xml version="1.0" encoding="ISO-8859-1"?>
<!-- XML generated by UTFXML Version 2.2 built 19-Aug-2010 -->
<UTFXML filename="bm_wplat_scrap3.3db" path="BMOD\SOLAR\MISC">
   <UTF_ROOT>
      <VMeshLibrary>
         <bm_wplat_scrap3.lod0-112.vms include="bm_wplat_scrap3_3db\lod0-112.vms.xml"/>
      </VMeshLibrary>
      <Exporter_Version name="Exporter Version" type="text">MAXLancer Tools 0.98</Exporter_Version>
      <VMeshPart>
         <VMeshRef type="VMeshRef">
            <!-- header size  --> 60,
            <!-- vmesh lib    --> bm_wplat_scrap3.lod0-112.vms,
            <!-- start vert   --> 0,
            <!-- num verts    --> 50,
            <!-- start index  --> 0,
            <!-- num indices  --> 171,
            <!-- start mesh   --> 0,
            <!-- num meshes   --> 2,
            <!-- bounding box -->  3.885087,    4.1526842,  3.9782832,
                                  -3.885087,   -4.1526842, -3.978287,
            <!-- center       --> -0.40597352,  2.1745465,  0.043666292,
            <!-- radius       --> 7.7866006
         </VMeshRef>
      </VMeshPart>
      <Hardpoints>
         <Fixed>
            <HpRunningLight01>
               <Position type="Vector">-3.8037376, 0.57545614, -1.6997579</Position>
               <Orientation type="Matrix">
                    0.2893495300,  13.098899e-09,   0.9572235300,
                  -45.270159e-09,   1.0000000000,   0.0000000000,
                   -0.9572235300, -43.333660e-09,   0.2893495300
               </Orientation>
            </HpRunningLight01>
            <HpRunningLight02>
               <Position type="Vector">3.4288607, 0.71876955, 1.7078522</Position>
               <Orientation type="Matrix">
                   -0.4782384900,  462.57182e-09,  -0.8782300400,
                   1.9073486e-06,   1.0000000000, -511.93388e-09,
                    0.8782300400, -1.9199174e-06,  -0.4782384900
               </Orientation>
            </HpRunningLight02>
         </Fixed>
         <Revolute>
            <HpTurret01>
               <Position type="Vector">0, 4.1256957, 0</Position>
               <Orientation type="Matrix">
                    1.0000000000,   0.0000000000,   0.0000000000,
                    0.0000000000,   1.0000000000,   0.0000000000,
                    0.0000000000,   0.0000000000,   1.0000000000
               </Orientation>
               <Axis type="Vector">0, 1, 0</Axis>
               <Min type="float">-6.2831855</Min>
               <Max type="float">6.2831855</Max>
            </HpTurret01>
            <HpTurret02>
               <Position type="Vector">-68.216217e-9, 1.9060036, 0</Position>
               <Orientation type="Matrix">
                   -1.0000000000,  87.422777e-09,   0.0000000000,
                  -87.422777e-09,  -1.0000000000,   0.0000000000,
                    0.0000000000,   0.0000000000,   1.0000000000
               </Orientation>
               <Axis type="Vector">0, 1, 0</Axis>
               <Min type="float">-6.2831855</Min>
               <Max type="float">6.2831855</Max>
            </HpTurret02>
         </Revolute>
      </Hardpoints>
   </UTF_ROOT>
</UTFXML>
