<?xml version="1.0" encoding="ISO-8859-1"?>
<!-- XML generated by UTFXML Version 2.2 built 19-Aug-2010 -->
<UTFXML filename="bmod_large_shield.ale" path="BMOD\FX\EQUIPMENT">
   <UTF_ROOT>
      <ALEffectLib>
         <ALEffectLib type="ALEffectLib" version="1" count="1">
            <effect name="gf_li_shield01_big">
               <fx count="5">
                   8, 32768, 1, 0xEE223B51
                   5,     8, 0, gf_li_shield01_big_hotspot_Cone.emt
                   9,     8, 0, gf_li_shield01_big_cube.emt
                   4,     8, 0, gf_li_shield01_big_hotspot.app
                  10,     8, 0, gf_li_shield01_big.app
               </fx>
               <pairs count="2">
                   5,  4
                   9, 10
               </pairs>
            </effect>
         </ALEffectLib>
      </ALEffectLib>
      <AlchemyNodeLibrary>
         <AlchemyNodeLibrary type="AlchemyNodeLibrary" version="1.1" count="4">
            <node name="FxPerpAppearance">
               <effect type="name"  name="Node_Name">gf_li_shield01_big_hotspot.app</effect>
               <effect type="float" name="Node_LifeSpan">3</effect>
               <effect type="xform" name="Node_Transform">0x435
                  <single type="4" count="1">
                     0: 0
                  </single>
                  <single type="4" count="1">
                     0: 0
                  </single>
                  <single type="4" count="1">
                     0: 0
                  </single>
                  <single type="4" count="1">
                     0: 0
                  </single>
                  <single type="4" count="1">
                     0: 0
                  </single>
                  <single type="4" count="1">
                     0: 0
                  </single>
                  <single type="4" count="1">
                     0: 1
                  </single>
                  <single type="4" count="1">
                     0: 1
                  </single>
                  <single type="4" count="1">
                     0: 1
                  </single>
               </effect>
               <effect type="fanim" name="Appearance_LODCurve">
                  <float_header type="4" count="1">
                     0:
                        <float type="4" count="1">
                           0: 1
                        </float>
                  </float_header>
               </effect>
               <effect type="bool"  name="BasicApp_TriTexture">false</effect>
               <effect type="bool"  name="BasicApp_QuadTexture">true</effect>
               <effect type="bool"  name="BasicApp_MotionBlur">false</effect>
               <effect type="canim" name="BasicApp_Color">
                  <rgb_header type="4" count="1">
                     0:
                        <rgb type="4" count="2">
                             0.1781609200: 1, 1, 1
                             1.0000000000: 0, 0, 0.82352942
                        </rgb>
                  </rgb_header>
               </effect>
               <effect type="fanim" name="BasicApp_Alpha">
                  <float_header type="4" count="1">
                     0:
                        <float type="1" count="2">
                             0.0000000000: 1
                             0.9938340200: 0.001241
                        </float>
                  </float_header>
               </effect>
               <effect type="fanim" name="BasicApp_Size">
                  <float_header type="4" count="1">
                     0:
                        <float type="4" count="1">
                           0: 16
                        </float>
                  </float_header>
               </effect>
               <effect type="fanim" name="BasicApp_HToVAspect">
                  <float_header type="4" count="1">
                     0:
                        <float type="4" count="1">
                           0: 1
                        </float>
                  </float_header>
               </effect>
               <effect type="fanim" name="BasicApp_Rotate">
                  <float_header type="4" count="1">
                     0:
                        <float type="4" count="1">
                           0: 0
                        </float>
                  </float_header>
               </effect>
               <effect type="name"  name="BasicApp_TexName">small-flare</effect>
               <effect type="ipair" name="BasicApp_BlendInfo">5, 2</effect>
               <effect type="bool"  name="BasicApp_UseCommonTexFrame">false</effect>
               <effect type="fanim" name="BasicApp_TexFrame">
                  <float_header type="4" count="1">
                     0:
                        <float type="4" count="1">
                           0: 0
                        </float>
                  </float_header>
               </effect>
               <effect type="vanim" name="BasicApp_CommonTexFrame">
                  <single type="4" count="1">
                     0: 0
                  </single>
               </effect>
               <effect type="bool"  name="BasicApp_FlipTexU">false</effect>
               <effect type="bool"  name="BasicApp_FlipTexV">false</effect>
               <effect type="bool"  name="RectApp_CenterOnPos">false</effect>
               <effect type="bool"  name="RectApp_ViewingAngleFade">false</effect>
               <effect type="fanim" name="RectApp_Scale">
                  <float_header type="4" count="1">
                     0:
                        <float type="4" count="1">
                           0: 1
                        </float>
                  </float_header>
               </effect>
               <effect type="fanim" name="RectApp_Length">
                  <float_header type="4" count="1">
                     0:
                        <float type="4" count="1">
                           0: 1
                        </float>
                  </float_header>
               </effect>
               <effect type="fanim" name="RectApp_Width">
                  <float_header type="4" count="1">
                     0:
                        <float type="4" count="1">
                           0: 1
                        </float>
                  </float_header>
               </effect>
            </node>
            <node name="FxPerpAppearance">
               <effect type="name"  name="Node_Name">gf_li_shield01_big.app</effect>
               <effect type="float" name="Node_LifeSpan">3</effect>
               <effect type="xform" name="Node_Transform">0x435
                  <single type="4" count="1">
                     0: 0
                  </single>
                  <single type="4" count="1">
                     0: 0
                  </single>
                  <single type="4" count="1">
                     0: 0
                  </single>
                  <single type="4" count="1">
                     0: 0
                  </single>
                  <single type="4" count="1">
                     0: 0
                  </single>
                  <single type="4" count="1">
                     0: 0
                  </single>
                  <single type="4" count="1">
                     0: 1
                  </single>
                  <single type="4" count="1">
                     0: 1
                  </single>
                  <single type="4" count="1">
                     0: 1
                  </single>
               </effect>
               <effect type="fanim" name="Appearance_LODCurve">
                  <float_header type="4" count="1">
                     0:
                        <float type="4" count="1">
                           0: 1
                        </float>
                  </float_header>
               </effect>
               <effect type="bool"  name="BasicApp_TriTexture">false</effect>
               <effect type="bool"  name="BasicApp_QuadTexture">true</effect>
               <effect type="bool"  name="BasicApp_MotionBlur">false</effect>
               <effect type="canim" name="BasicApp_Color">
                  <rgb_header type="4" count="1">
                     0:
                        <rgb type="4" count="2">
                             0.0000000000: 1, 1, 1
                             1.0000000000: 0.06666667, 0.06666667, 0.73333335
                        </rgb>
                  </rgb_header>
               </effect>
               <effect type="fanim" name="BasicApp_Alpha">
                  <float_header type="4" count="1">
                     0:
                        <float type="1" count="3">
                             0.0000000000: 0
                             0.4343119900: 1
                             1.0000000000: 0
                        </float>
                  </float_header>
               </effect>
               <effect type="fanim" name="BasicApp_Size">
                  <float_header type="4" count="1">
                     0:
                        <float type="4" count="2">
                             0.0000000000: 1
                             1.0000000000: 6.0220828
                        </float>
                  </float_header>
               </effect>
               <effect type="fanim" name="BasicApp_HToVAspect">
                  <float_header type="4" count="1">
                     0:
                        <float type="4" count="1">
                           0: 1
                        </float>
                  </float_header>
               </effect>
               <effect type="fanim" name="BasicApp_Rotate">
                  <float_header type="4" count="1">
                     0:
                        <float type="4" count="1">
                           0: 0
                        </float>
                  </float_header>
               </effect>
               <effect type="name"  name="BasicApp_TexName">kioncanring</effect>
               <effect type="ipair" name="BasicApp_BlendInfo">5, 2</effect>
               <effect type="bool"  name="BasicApp_UseCommonTexFrame">false</effect>
               <effect type="fanim" name="BasicApp_TexFrame">
                  <float_header type="4" count="1">
                     0:
                        <float type="4" count="1">
                           0: 0
                        </float>
                  </float_header>
               </effect>
               <effect type="vanim" name="BasicApp_CommonTexFrame">
                  <single type="4" count="1">
                     0: 0
                  </single>
               </effect>
               <effect type="bool"  name="BasicApp_FlipTexU">false</effect>
               <effect type="bool"  name="BasicApp_FlipTexV">false</effect>
               <effect type="bool"  name="RectApp_CenterOnPos">false</effect>
               <effect type="bool"  name="RectApp_ViewingAngleFade">false</effect>
               <effect type="fanim" name="RectApp_Scale">
                  <float_header type="4" count="1">
                     0:
                        <float type="4" count="1">
                           0: 32
                        </float>
                  </float_header>
               </effect>
               <effect type="fanim" name="RectApp_Length">
                  <float_header type="4" count="1">
                     0:
                        <float type="4" count="1">
                           0: 1
                        </float>
                  </float_header>
               </effect>
               <effect type="fanim" name="RectApp_Width">
                  <float_header type="4" count="1">
                     0:
                        <float type="4" count="1">
                           0: 1
                        </float>
                  </float_header>
               </effect>
            </node>
            <node name="FxConeEmitter">
               <effect type="name"  name="Node_Name">gf_li_shield01_big_hotspot_Cone.emt</effect>
               <effect type="float" name="Node_LifeSpan">1</effect>
               <effect type="xform" name="Node_Transform">0x435
                  <single type="4" count="1">
                     0: 0
                  </single>
                  <single type="4" count="1">
                     0: 0
                  </single>
                  <single type="4" count="1">
                     0: 0
                  </single>
                  <single type="4" count="1">
                     0: 0
                  </single>
                  <single type="4" count="1">
                     0: 0
                  </single>
                  <single type="4" count="1">
                     0: 0
                  </single>
                  <single type="4" count="1">
                     0: 1
                  </single>
                  <single type="4" count="1">
                     0: 1
                  </single>
                  <single type="4" count="1">
                     0: 1
                  </single>
               </effect>
               <effect type="fanim" name="Emitter_LODCurve">
                  <float_header type="4" count="1">
                     0:
                        <float type="4" count="1">
                           0: 1
                        </float>
                  </float_header>
               </effect>
               <effect type="int"   name="Emitter_InitialParticles">4</effect>
               <effect type="vanim" name="Emitter_Frequency">
                  <single type="4" count="1">
                     0: 100
                        <loop count="1">
                           0: 0, 0, 0
                        </loop>
                  </single>
               </effect>
               <effect type="vanim" name="Emitter_MaxParticles">
                  <single type="4" count="1">
                     0: 10000
                  </single>
               </effect>
               <effect type="vanim" name="Emitter_EmitCount">
                  <single type="4" count="1">
                     0: 0
                  </single>
               </effect>
               <effect type="vanim" name="Emitter_InitLifeSpan">
                  <single type="4" count="1">
                     0: 2
                  </single>
               </effect>
               <effect type="vanim" name="Emitter_Pressure">
                  <single type="4" count="1">
                     0: 10
                        <loop count="1">
                           -268e-6: 0.191067, 0, 0
                        </loop>
                  </single>
               </effect>
               <effect type="vanim" name="Emitter_VelocityApproach">
                  <single type="4" count="1">
                     0: 0
                  </single>
               </effect>
               <effect type="vanim" name="ConeEmitter_MinRadius">
                  <single type="4" count="1">
                     0: 0
                        <loop count="1">
                           0: 0, 0, 0
                        </loop>
                  </single>
               </effect>
               <effect type="vanim" name="ConeEmitter_MaxRadius">
                  <single type="4" count="1">
                     0: 1
                        <loop count="1">
                           0: 0, 0, 0
                        </loop>
                  </single>
               </effect>
               <effect type="vanim" name="ConeEmitter_MinSpread">
                  <single type="4" count="1">
                     0: 0
                        <loop count="1">
                           -268e-6: 0.051860999, 0, 0
                        </loop>
                  </single>
               </effect>
               <effect type="vanim" name="ConeEmitter_MaxSpread">
                  <single type="4" count="1">
                     0: 0
                        <loop count="1">
                           2.9932981: 10, 0, 0
                        </loop>
                  </single>
               </effect>
            </node>
            <node name="FxCubeEmitter">
               <effect type="name"  name="Node_Name">gf_li_shield01_big_cube.emt</effect>
               <effect type="float" name="Node_LifeSpan">3</effect>
               <effect type="xform" name="Node_Transform">0x435
                  <single type="4" count="1">
                     0: 0
                  </single>
                  <single type="4" count="1">
                     0: 0
                  </single>
                  <single type="4" count="1">
                     0: 0
                  </single>
                  <single type="4" count="1">
                     0: 0
                  </single>
                  <single type="4" count="1">
                     0: 0
                  </single>
                  <single type="4" count="1">
                     0: 0
                  </single>
                  <single type="4" count="1">
                     0: 1
                  </single>
                  <single type="4" count="1">
                     0: 1
                  </single>
                  <single type="4" count="1">
                     0: 1
                  </single>
               </effect>
               <effect type="fanim" name="Emitter_LODCurve">
                  <float_header type="4" count="1">
                     0:
                        <float type="4" count="1">
                           0: 1
                        </float>
                  </float_header>
               </effect>
               <effect type="int"   name="Emitter_InitialParticles">1</effect>
               <effect type="vanim" name="Emitter_Frequency">
                  <single type="4" count="1">
                     0: 100
                        <loop count="1">
                           1.003485: 0, 0, 0
                        </loop>
                  </single>
               </effect>
               <effect type="vanim" name="Emitter_MaxParticles">
                  <single type="4" count="1">
                     0: 10000
                  </single>
               </effect>
               <effect type="vanim" name="Emitter_EmitCount">
                  <single type="4" count="1">
                     0: 0
                  </single>
               </effect>
               <effect type="vanim" name="Emitter_InitLifeSpan">
                  <single type="4" count="1">
                     0: 2
                        <loop count="1">
                           0.002949: 0.89546198, 0, 0
                        </loop>
                  </single>
               </effect>
               <effect type="vanim" name="Emitter_Pressure">
                  <single type="4" count="1">
                     0: 10
                        <loop count="1">
                           0.002949: 0.191067, 0, 0
                        </loop>
                  </single>
               </effect>
               <effect type="vanim" name="Emitter_VelocityApproach">
                  <single type="4" count="1">
                     0: 0
                  </single>
               </effect>
               <effect type="vanim" name="CubeEmitter_Width">
                  <single type="4" count="1">
                     0: 5
                        <loop count="1">
                           0.015817: 2.0095019, 0, 0
                        </loop>
                  </single>
               </effect>
               <effect type="vanim" name="CubeEmitter_Height">
                  <single type="4" count="1">
                     0: 5
                        <loop count="1">
                           -0.003485: 0.196777, 0, 0
                        </loop>
                  </single>
               </effect>
               <effect type="vanim" name="CubeEmitter_Depth">
                  <single type="4" count="1">
                     0: 5
                        <loop count="1">
                           0.009383: 2.001241, 0, 0
                        </loop>
                  </single>
               </effect>
               <effect type="vanim" name="CubeEmitter_MinSpread">
                  <single type="4" count="1">
                     0: 0
                  </single>
               </effect>
               <effect type="vanim" name="CubeEmitter_MaxSpread">
                  <single type="4" count="1">
                     0: 15
                        <loop count="1">
                           0.012601: 3.9937971, 0, 0
                        </loop>
                  </single>
               </effect>
            </node>
         </AlchemyNodeLibrary>
      </AlchemyNodeLibrary>
   </UTF_ROOT>
</UTFXML>
