<?xml version="1.0" encoding="ISO-8859-1"?>
<!-- XML generated by UTFXML Version 2.2 built 19-Aug-2010 -->
<UTFXML filename="planet_gasgrncld.txm" path="SOLAR\PLANETS">
   <UTF_ROOT>
      <Exporter_Version name="Exporter Version" type="text">May 28 2002 17:23:51</Exporter_Version>
      <Texture_library name="Texture library">
         <gasgrncldcap>
            <MIPS type="file" filename="planet_gasgrncld_txm\gasgrncldcap.dds"/>
         </gasgrncldcap>
         <gasgrncld02>
            <MIPS type="file" filename="planet_gasgrncld_txm\gasgrncld02.dds"/>
         </gasgrncld02>
         <gasgrncld01>
            <MIPS type="file" filename="planet_gasgrncld_txm\gasgrncld01.dds"/>
         </gasgrncld01>
      </Texture_library>
   </UTF_ROOT>
</UTFXML>
